{
  "track_id": "portfolio_tabs_20260209",
  "type": "feature",
  "status": "new",
  "created_at": "2026-02-09T22:11:00Z",
  "updated_at": "2026-02-09T22:11:00Z",
  "description": "Реализовать возможность просматривать историю сделок ценных бумаг по счету. В окне Positions реализовать функционал вкладок. Текущий функционал с позициями оставить с названием Positions, создать новую вкладку History и вкладку Orders. Переключение вкладко можно сделать стрелками - вправо, влево. Во вкладке History должна быть таблица, оформление такое же как у Positions, со столбцами - Операция (покупка/продажа), Инструмент, Количество, Сумма, Цена за штуку, дата и время. Во вкладке Orders должны отображаться не исполненные заявки со столбцами - Инструмент, Режим, Тип, Заявлено, Активация, Цена, Время, Исполнено, Срок, Статус."
}
